Workbook

Sheet Cover
B2: FINANCIAL MODEL: AGENTIC AI INDUSTRY ANALYSIS
B4: Developed by: Alpha Analyst
B5: Date: 8 February 2024
B8: TABLE OF CONTENTS
B10: 1. Cover
B11: =HYPERLINK("#Assumptions!A1", "2. Assumptions") -> 2. Assumptions
B12: =HYPERLINK("#Calculations!A1","3. Calculations") -> 3. Calculations
B13: =HYPERLINK("#Financials!A1","4. Financials") -> 4. Financials
B14: =HYPERLINK("#Dashboard!A1","5. Dashboard") -> 5. Dashboard

Sheet Assumptions
A1: =HYPERLINK("#Cover!A1", "<< Back to Cover") -> << Back to Cover
B4: Column1 | C4: Year 1 | D4: Year 2 | E4: Year 3 | F4: Year 4 | G4: Year 5
B5: Section 1: Market Assumptions
B6: Global AI Agent Market ($ Billions) | C6: 500
B7: Annual Market Growth (%) | C7: 0.25 | D7: =C7 -> 0.25 | E7: =D7 -> 0.25 | F7: =E7 -> 0.25 | G7: =F7 -> 0.25
B10: Section 2: Revenue Drivers
B11: Avg. Monthly Subscription (per Agent) | C11: 500
B12: Number of Agents (Initial) | C12: 5000
B15: Section 3: Operating Costs
B16: API/Compute Cost (% of Revenue) | C16: 0.6
B17: Annual Salary per AI Engineer ($) | C17: 150000
B18: Number of Engineers (Year 1) | C18: 10
B19: Annual Headcount Growth (Nos.) | C19: 2

Sheet Calculations
A1: =HYPERLINK("#Cover!A1", "<< Back to Cover") -> << Back to Cover
C3: Year 1 | D3: Year 2 | E3: Year 3 | F3: Year 4 | G3: Year 5
B4: Revenue Calculation
B6: Number of Agents | C6: =Assumptions!C12 -> 5000 | D6: =C6 * (1 + Assumptions!D7) -> 6250 | E6: =D6 * (1 + Assumptions!E7) -> 7812.5 | F6: =E6 * (1 + Assumptions!F7) -> 9765.625 | G6: =F6 * (1 + Assumptions!G7) -> 12207.031
B7: Monthly Revenue per Agent | C7: =Assumptions!C11 -> 500 | D7: =C7 -> 500 | E7: =D7 -> 500 | F7: =E7 -> 500 | G7: =F7 -> 500
B8: Total Annual Revenue | C8: =C6*C7*12 -> 30000000 | D8: =D6*D7*12 -> 37500000 | E8: =E6*E7*12 -> 46875000 | F8: =F6*F7*12 -> 58593750 | G8: =G6*G7*12 -> 73242188
B11: API & Compute Costs | C11: =C8 * Assumptions!$C$16 -> 18000000 | D11: =D8 * Assumptions!$C$16 -> 22500000 | E11: =E8 * Assumptions!$C$16 -> 28125000 | F11: =F8 * Assumptions!$C$16 -> 35156250 | G11: =G8 * Assumptions!$C$16 -> 43945312
B12: Number of Engineers | C12: =Assumptions!$C$18 -> 10 | D12: =C12 + Assumptions!$C$19 -> 12 | E12: =D12 + Assumptions!$C$19 -> 14 | F12: =E12 + Assumptions!$C$19 -> 16 | G12: =F12 + Assumptions!$C$19 -> 18
B13: Engineering Salaries | C13: =C12 * Assumptions!$C$17 -> 1500000 | D13: =D12 * Assumptions!$C$17 -> 1800000 | E13: =E12 * Assumptions!$C$17 -> 2100000 | F13: =F12 * Assumptions!$C$17 -> 2400000 | G13: =G12 * Assumptions!$C$17 -> 2700000
B14: Total Operating Costs | C14: =C11 + C13 -> 19500000 | D14: =D11 + D13 -> 24300000 | E14: =E11 + E13 -> 30225000 | F14: =F11 + F13 -> 37556250 | G14: =G11 + G13 -> 46645312
B16: EBITDA | C16: =C8 - C14 -> 10500000 | D16: =D8 - D14 -> 13200000 | E16: =E8 - E14 -> 16650000 | F16: =F8 - F14 -> 21037500 | G16: =G8 - G14 -> 26596875

Sheet Financials
A1: =HYPERLINK("#Cover!A1", "<< Back to Cover") -> << Back to Cover
B4: PROJECTED INCOME STATEMENT (AGENTIC AI) | C4: Year 1 | D4: Year 2 | E4: Year 3 | F4: Year 4 | G4: Year 5
B6: Revenue | C6: =Calculations!C8 -> 30000000 | D6: =Calculations!D8 -> 37500000 | E6: =Calculations!E8 -> 46875000 | F6: =Calculations!F8 -> 58593750 | G6: =Calculations!G8 -> 73242188
B7: Cost of Goods Sold (COGS) | C7: =Calculations!C11 -> 18000000 | D7: =Calculations!D11 -> 22500000 | E7: =Calculations!E11 -> 28125000 | F7: =Calculations!F11 -> 35156250 | G7: =Calculations!G11 -> 43945312
B8: Gross Profit | C8: =C6 - C7 -> 12000000 | D8: =D6 - D7 -> 15000000 | E8: =E6 - E7 -> 18750000 | F8: =F6 - F7 -> 23437500 | G8: =G6 - G7 -> 29296875
B9: Operating Expenses (OpEx) | C9: =Calculations!C13 -> 1500000 | D9: =Calculations!D13 -> 1800000 | E9: =Calculations!E13 -> 2100000 | F9: =Calculations!F13 -> 2400000 | G9: =Calculations!G13 -> 2700000
B10: EBITDA | C10: =C8 - C9 -> 10500000 | D10: =D8 - D9 -> 13200000 | E10: =E8 - E9 -> 16650000 | F10: =F8 - F9 -> 21037500 | G10: =G8 - G9 -> 26596875
B11: Taxes | C11: =C10 * 25% -> 2625000 | D11: =D10 * 25% -> 3300000 | E11: =E10 * 25% -> 4162500 | F11: =F10 * 25% -> 5259375 | G11: =G10 * 25% -> 6649218.8
B12: Net Income | C12: =C10 - C11 -> 7875000 | D12: =D10 - D11 -> 9900000 | E12: =E10 - E11 -> 12487500 | F12: =F10 - F11 -> 15778125 | G12: =G10 - G11 -> 19947656

Sheet Dashboard
A1: =HYPERLINK("#Cover!A1", "<< Back to Cover") -> << Back to Cover
B2: MODEL SENSITIVITY & INTERACTIVITY
F3: Blue Text = User Inputs (You can change these)
B4: Go to the 'Assumptions' sheet and change the input (blue numbers) to see live updates here! | F4: Black Text = Calculations/Formulas (Locked)
F5: Blue Underline = Navigation Links
B8: Year 5 Revenue | C8: =Financials!G6 -> 73242188
B9: Year 5 Net Income | C9: =Financials!G12 -> 19947656
